dataclass_dict_convert/__init__.py
dataclass_dict_convert/autoclass_convert.py
dataclass_dict_convert/convert.py
dataclass_dict_convert/dataclass_utils.py
dataclass_dict_convert/rfc3339.py
dataclass_dict_convert-1.7.4.dist-info/LICENSE
dataclass_dict_convert-1.7.4.dist-info/METADATA
dataclass_dict_convert-1.7.4.dist-info/WHEEL
dataclass_dict_convert-1.7.4.dist-info/top_level.txt
dataclass_dict_convert-1.7.4.dist-info/RECORD
