Metadata-Version: 2.1
Name: dataclass-dict-convert
Version: 1.7.4
Summary: Convert between Dataclasses and dict/json
Home-page: https://gitlab.ilabt.imec.be/wvdemeer/dataclass-dict-convert
Author: Wim Van de Meerssche
Author-email: wim.vandemeerssche@ugent.be
License: MIT
Classifier: License :: OSI Approved :: MIT License
Classifier: Programming Language :: Python :: 3
Classifier: Programming Language :: Python :: 3.7
Requires-Python: >=3.7
License-File: LICENSE
Requires-Dist: python-dateutil
Requires-Dist: stringcase
